denzel/Dockerfile
denzel/Dockerfile.gpu
denzel/__init__.py
denzel/docker-compose.yml
denzel/requirements.sh
denzel/requirements.txt
denzel/app/__init__.py
denzel/app/tasks.py
denzel/app/assets/info.txt
denzel/app/logic/__init__.py
denzel/app/logic/pipeline.py
denzel/entrypoints/api.sh
denzel/entrypoints/denzel.sh
denzel/entrypoints/monitor.sh
denzel_cli/__init__.py
denzel_cli/commands.py
denzel_cli/config.py
denzel_cli/utils.py
denzel_cli/scripts/__init__.py
denzel_cli/scripts/cli.py
denzel-0.3.0.dist-info/LICENSE
denzel-0.3.0.dist-info/METADATA
denzel-0.3.0.dist-info/WHEEL
denzel-0.3.0.dist-info/entry_points.txt
denzel-0.3.0.dist-info/top_level.txt
denzel-0.3.0.dist-info/RECORD
