Metadata-Version: 2.1
Name: denzel
Version: 0.3.0
Summary: UNKNOWN
Home-page: UNKNOWN
Author: UNKNOWN
Author-email: UNKNOWN
License: UNKNOWN
Platform: UNKNOWN
Requires-Dist: Click
Requires-Dist: docker
